{
  "heading": "Building the Future with Technology",
  "description": "We combine strategy, design, and engineering to create scalable digital products that evolve with your business.",
  "cta": {
    "label": "Explore Solutions",
    "href": "/solutions"
  },
  "steps": [
    {
      "id": 1,
      "title": "Product Discovery & Strategy",
      "subtitle": "User research, requirements analysis, roadmap planning"
    },
    {
      "id": 2,
      "title": "UI/UX Design & Prototyping",
      "subtitle": "User-centered interfaces focused on usability and performance"
    },
    {
      "id": 3,
      "title": "Product Engineering",
      "subtitle": "Frontend, backend, APIs, scalable architecture"
    },
    {
      "id": 4,
      "title": "Cloud & DevOps",
      "subtitle": "Secure deployment, CI/CD, monitoring and scalability"
    },
    {
      "id": 5,
      "title": "AI Automation & Optimization",
      "subtitle": "Smart features, performance tuning, continuous improvement"
    }
  ]
}
